Workbook

Sheet Start Here
A1: VMValue | Research Starter Workbook
A3: Purpose
A4: This workbook is a reproducible teaching prototype for a proposed explainable, risk-aware VM rightsizing review process. Every VM metric in the inventory is synthetic. Outputs are modeled cost proxies, not measured savings, and statuses are not production resize instructions.
A7: What to do first
A8: 1. Open Assumptions and replace the illustrative cost rates with values appropriate to a clearly defined scenario.
A9: 2. Open VM Inventory and inspect the sample rows. Every row is hypothetical; do not present it as real telemetry.
A10: 3. Change the editable inputs (blue cells) to test how recommendations and estimated costs change.
A11: 4. Treat every right-sizing suggestion as a candidate for review, not an instruction to change production systems.
A12: 5. Use the workbook to learn the problem. The paper's research contribution must be defined after a literature audit.
A15: Research integrity
A16: All example VM names, utilization figures, cost rates, and calculated savings are synthetic illustrations. They are included to demonstrate the analysis workflow, not as empirical results or evidence of novelty.

Sheet Summary
A1: VMValue | Scenario Summary | B1: Calculated value | C1: Interpretation
A2: Current monthly allocation-cost proxy | B2: =SUM('VM Inventory'!T2:T13) -> 2280 | C2: Synthetic scenario; not an invoice or vendor quote.
A3: Candidate monthly allocation-cost proxy | B3: =SUM('VM Inventory'!U2:U13) -> 1608 | C3: Candidate sizing before safety gates.
A4: Gross modeled difference / month | B4: =B2-B3 -> 672 | C4: Includes held VMs and a negative row; not realizable savings.
A5: Annualized gross modeled difference | B5: =B4*12 -> 8064 | C5: Simple arithmetic only; not a forecast.
A6: Positive gross opportunities / month | B6: =SUMIF('VM Inventory'!V2:V13,">0",'VM Inventory'!V2:V13) -> 678 | C6: All rows, including held candidates.
A7: Risk-adjusted priority proxy / month | B7: =SUM('VM Inventory'!AC2:AC13) -> 616.8 | C7: Heuristic score, not an expected-value estimate.
A8: Review-candidate gross difference / month | B8: =SUMIF('VM Inventory'!AD2:AD13,"REVIEW CANDIDATE",'VM Inventory'!V2:V13) -> 525 | C8: Rows that pass the illustrative hard gates; still require human review.
A9: Count: review candidates | B9: =COUNTIF('VM Inventory'!AD2:AD13,"REVIEW CANDIDATE") -> 6 | C9: Not approval to resize.
A10: Count: hold / expert review | B10: =COUNTIF('VM Inventory'!AD2:AD13,"HOLD / EXPERT REVIEW") -> 6 | C10: Hard-gated due to criticality, telemetry, pressure, demand, or context.
A11: Important caveat | B11: ALL INVENTORY VALUES ARE SYNTHETIC | C11: Do not describe these outputs as measured savings or production findings.

Sheet Assumptions
A1: Editable Scenario Assumptions
A2: Parameter | B2: Illustrative value | C2: Unit / interpretation | D2: Notes
A3: Monthly charge per allocated vCPU | B3: 12 | C3: currency units / vCPU / month | D3: Example chargeback proxy; replace with your scenario's rate.
A4: Monthly charge per allocated GB RAM | B4: 3 | C4: currency units / GB / month | D4: Example chargeback proxy; not a universal market price.
A5: Target CPU utilization after sizing | B5: 0.7 | C5: fraction of provisioned vCPU | D5: Planning assumption; tune and justify for the workload.
A6: Target memory working-set utilization | B6: 0.8 | C6: fraction of allocated RAM | D6: Planning assumption; never use without workload-specific validation.
A7: Required host/cluster reserve | B7: 0.25 | C7: fraction of capacity reserved | D7: A simple reserve assumption for scenario analysis, not a HA guarantee.
A8: Representative telemetry window | B8: 30 | C8: days | D8: Illustrative scenario setting used for the worked example; not real telemetry.

Sheet VM Inventory
A1: VM ID | B1: Workload class | C1: Critical? (Yes/No) | D1: Allocated vCPU | E1: P95 CPU util (%) | F1: Allocated RAM (GB) | G1: P95 active RAM (GB) | H1: Telemetry complete? (Yes/No) | I1: Telemetry days | J1: Daily P95 CPU CV (synthetic) | K1: CPU Ready % (synthetic) | L1: Co-Stop % (synthetic) | M1: Ballooning? (Yes/No) | N1: Swap? (Yes/No) | O1: Owner confirmed? (Yes/No) | P1: Vendor constraints verified? (Yes/No) | Q1: Estimated CPU demand (vCPU) | R1: Candidate vCPU | S1: Candidate RAM (GB) | T1: Current monthly cost proxy | U1: Candidate monthly cost proxy | V1: Gross difference / month | W1: E1 Coverage | X1: E2 Stability | Y1: E3 Pressure | Z1: E4 Context | AA1: Evidence score E | AB1: Confidence label | AC1: Risk-adjusted priority proxy / month | AD1: Decision status | AE1: Notes
A2: VM-01 | B2: Web server | C2: No | D2: 8 | E2: 22 | F2: 32 | G2: 9 | H2: Yes | I2: 30 | J2: 0.2 | K2: 2 | L2: 1 | M2: No | N2: No | O2: Yes | P2: Yes | Q2: =D2*E2/100 -> 1.76 | R2: =MAX(1,ROUNDUP(Q2/Assumptions!$B$5-0.000000001,0)) -> 3 | S2: =MAX(1,ROUNDUP(G2/Assumptions!$B$6-0.000000001,0)) -> 12 | T2: =D2*Assumptions!$B$3+F2*Assumptions!$B$4 -> 192 | U2: =R2*Assumptions!$B$3+S2*Assumptions!$B$4 -> 72 | V2: =T2-U2 -> 120 | W2: =IF(AND(H2="Yes",I2>=30),1,IF(AND(H2="Yes",I2>=14),0.5,0)) -> 1 | X2: =IF(J2<0.3,1,IF(J2<0.6,0.5,0)) -> 1 | Y2: =IF(OR(K2>10,L2>5,M2="Yes",N2="Yes"),0,IF(OR(K2>=5,L2>=3,M2="Minor",N2="Minor"),0.5,1)) -> 1 | Z2: =IF(OR(C2="Yes",O2<>"Yes",P2<>"Yes"),0,1) -> 1 | AA2: =AVERAGE(W2:Z2) -> 1 | AB2: =IF(AA2>=0.75,"High",IF(AA2>=0.4,"Medium","Low")) -> High | AC2: =MAX(0,V2)*IF(AB2="High",1,IF(AB2="Medium",0.6,0.2)) -> 120 | AD2: =IF(OR(C2="Yes",H2<>"Yes",E2>=70,G2>=F2,Y2=0,Z2=0),"HOLD / EXPERT REVIEW",IF(V2>0,"REVIEW CANDIDATE","NO POSITIVE SAVING")) -> REVIEW CANDIDATE | AE2: Hypothetical low-utilization example
A3: VM-02 | B3: Database | C3: Yes | D3: 8 | E3: 62 | F3: 64 | G3: 48 | H3: Yes | I3: 30 | J3: 0.4 | K3: 3 | L3: 2 | M3: No | N3: No | O3: Yes | P3: Yes | Q3: =D3*E3/100 -> 4.96 | R3: =MAX(1,ROUNDUP(Q3/Assumptions!$B$5-0.000000001,0)) -> 8 | S3: =MAX(1,ROUNDUP(G3/Assumptions!$B$6-0.000000001,0)) -> 60 | T3: =D3*Assumptions!$B$3+F3*Assumptions!$B$4 -> 288 | U3: =R3*Assumptions!$B$3+S3*Assumptions!$B$4 -> 276 | V3: =T3-U3 -> 12 | W3: =IF(AND(H3="Yes",I3>=30),1,IF(AND(H3="Yes",I3>=14),0.5,0)) -> 1 | X3: =IF(J3<0.3,1,IF(J3<0.6,0.5,0)) -> 0.5 | Y3: =IF(OR(K3>10,L3>5,M3="Yes",N3="Yes"),0,IF(OR(K3>=5,L3>=3,M3="Minor",N3="Minor"),0.5,1)) -> 1 | Z3: =IF(OR(C3="Yes",O3<>"Yes",P3<>"Yes"),0,1) -> 0 | AA3: =AVERAGE(W3:Z3) -> 0.625 | AB3: =IF(AA3>=0.75,"High",IF(AA3>=0.4,"Medium","Low")) -> Medium | AC3: =MAX(0,V3)*IF(AB3="High",1,IF(AB3="Medium",0.6,0.2)) -> 7.2 | AD3: =IF(OR(C3="Yes",H3<>"Yes",E3>=70,G3>=F3,Y3=0,Z3=0),"HOLD / EXPERT REVIEW",IF(V3>0,"REVIEW CANDIDATE","NO POSITIVE SAVING")) -> HOLD / EXPERT REVIEW | AE3: Critical workload; hard hold pending owner approval
A4: VM-03 | B4: Monitoring | C4: No | D4: 4 | E4: 18 | F4: 16 | G4: 5 | H4: Yes | I4: 30 | J4: 0.2 | K4: 2 | L4: 1 | M4: No | N4: No | O4: Yes | P4: Yes | Q4: =D4*E4/100 -> 0.72 | R4: =MAX(1,ROUNDUP(Q4/Assumptions!$B$5-0.000000001,0)) -> 2 | S4: =MAX(1,ROUNDUP(G4/Assumptions!$B$6-0.000000001,0)) -> 7 | T4: =D4*Assumptions!$B$3+F4*Assumptions!$B$4 -> 96 | U4: =R4*Assumptions!$B$3+S4*Assumptions!$B$4 -> 45 | V4: =T4-U4 -> 51 | W4: =IF(AND(H4="Yes",I4>=30),1,IF(AND(H4="Yes",I4>=14),0.5,0)) -> 1 | X4: =IF(J4<0.3,1,IF(J4<0.6,0.5,0)) -> 1 | Y4: =IF(OR(K4>10,L4>5,M4="Yes",N4="Yes"),0,IF(OR(K4>=5,L4>=3,M4="Minor",N4="Minor"),0.5,1)) -> 1 | Z4: =IF(OR(C4="Yes",O4<>"Yes",P4<>"Yes"),0,1) -> 1 | AA4: =AVERAGE(W4:Z4) -> 1 | AB4: =IF(AA4>=0.75,"High",IF(AA4>=0.4,"Medium","Low")) -> High | AC4: =MAX(0,V4)*IF(AB4="High",1,IF(AB4="Medium",0.6,0.2)) -> 51 | AD4: =IF(OR(C4="Yes",H4<>"Yes",E4>=70,G4>=F4,Y4=0,Z4=0),"HOLD / EXPERT REVIEW",IF(V4>0,"REVIEW CANDIDATE","NO POSITIVE SAVING")) -> REVIEW CANDIDATE | AE4: Hypothetical
A5: VM-04 | B5: Application server | C5: No | D5: 12 | E5: 35 | F5: 48 | G5: 22 | H5: Yes | I5: 30 | J5: 0.25 | K5: 2.5 | L5: 1.5 | M5: No | N5: No | O5: Yes | P5: Yes | Q5: =D5*E5/100 -> 4.2 | R5: =MAX(1,ROUNDUP(Q5/Assumptions!$B$5-0.000000001,0)) -> 6 | S5: =MAX(1,ROUNDUP(G5/Assumptions!$B$6-0.000000001,0)) -> 28 | T5: =D5*Assumptions!$B$3+F5*Assumptions!$B$4 -> 288 | U5: =R5*Assumptions!$B$3+S5*Assumptions!$B$4 -> 156 | V5: =T5-U5 -> 132 | W5: =IF(AND(H5="Yes",I5>=30),1,IF(AND(H5="Yes",I5>=14),0.5,0)) -> 1 | X5: =IF(J5<0.3,1,IF(J5<0.6,0.5,0)) -> 1 | Y5: =IF(OR(K5>10,L5>5,M5="Yes",N5="Yes"),0,IF(OR(K5>=5,L5>=3,M5="Minor",N5="Minor"),0.5,1)) -> 1 | Z5: =IF(OR(C5="Yes",O5<>"Yes",P5<>"Yes"),0,1) -> 1 | AA5: =AVERAGE(W5:Z5) -> 1 | AB5: =IF(AA5>=0.75,"High",IF(AA5>=0.4,"Medium","Low")) -> High | AC5: =MAX(0,V5)*IF(AB5="High",1,IF(AB5="Medium",0.6,0.2)) -> 132 | AD5: =IF(OR(C5="Yes",H5<>"Yes",E5>=70,G5>=F5,Y5=0,Z5=0),"HOLD / EXPERT REVIEW",IF(V5>0,"REVIEW CANDIDATE","NO POSITIVE SAVING")) -> REVIEW CANDIDATE | AE5: Hypothetical
A6: VM-05 | B6: Build runner | C6: No | D6: 8 | E6: 78 | F6: 16 | G6: 11 | H6: Yes | I6: 30 | J6: 0.25 | K6: 2 | L6: 1 | M6: No | N6: No | O6: Yes | P6: Yes | Q6: =D6*E6/100 -> 6.24 | R6: =MAX(1,ROUNDUP(Q6/Assumptions!$B$5-0.000000001,0)) -> 9 | S6: =MAX(1,ROUNDUP(G6/Assumptions!$B$6-0.000000001,0)) -> 14 | T6: =D6*Assumptions!$B$3+F6*Assumptions!$B$4 -> 144 | U6: =R6*Assumptions!$B$3+S6*Assumptions!$B$4 -> 150 | V6: =T6-U6 -> -6 | W6: =IF(AND(H6="Yes",I6>=30),1,IF(AND(H6="Yes",I6>=14),0.5,0)) -> 1 | X6: =IF(J6<0.3,1,IF(J6<0.6,0.5,0)) -> 1 | Y6: =IF(OR(K6>10,L6>5,M6="Yes",N6="Yes"),0,IF(OR(K6>=5,L6>=3,M6="Minor",N6="Minor"),0.5,1)) -> 1 | Z6: =IF(OR(C6="Yes",O6<>"Yes",P6<>"Yes"),0,1) -> 1 | AA6: =AVERAGE(W6:Z6) -> 1 | AB6: =IF(AA6>=0.75,"High",IF(AA6>=0.4,"Medium","Low")) -> High | AC6: =MAX(0,V6)*IF(AB6="High",1,IF(AB6="Medium",0.6,0.2)) -> 0 | AD6: =IF(OR(C6="Yes",H6<>"Yes",E6>=70,G6>=F6,Y6=0,Z6=0),"HOLD / EXPERT REVIEW",IF(V6>0,"REVIEW CANDIDATE","NO POSITIVE SAVING")) -> HOLD / EXPERT REVIEW | AE6: High P95 CPU; hold for workload-specific review; no modeled savings
A7: VM-06 | B7: File service | C7: Yes | D7: 4 | E7: 28 | F7: 64 | G7: 44 | H7: Yes | I7: 30 | J7: 0.4 | K7: 3 | L7: 2 | M7: No | N7: No | O7: Yes | P7: Yes | Q7: =D7*E7/100 -> 1.12 | R7: =MAX(1,ROUNDUP(Q7/Assumptions!$B$5-0.000000001,0)) -> 2 | S7: =MAX(1,ROUNDUP(G7/Assumptions!$B$6-0.000000001,0)) -> 55 | T7: =D7*Assumptions!$B$3+F7*Assumptions!$B$4 -> 240 | U7: =R7*Assumptions!$B$3+S7*Assumptions!$B$4 -> 189 | V7: =T7-U7 -> 51 | W7: =IF(AND(H7="Yes",I7>=30),1,IF(AND(H7="Yes",I7>=14),0.5,0)) -> 1 | X7: =IF(J7<0.3,1,IF(J7<0.6,0.5,0)) -> 0.5 | Y7: =IF(OR(K7>10,L7>5,M7="Yes",N7="Yes"),0,IF(OR(K7>=5,L7>=3,M7="Minor",N7="Minor"),0.5,1)) -> 1 | Z7: =IF(OR(C7="Yes",O7<>"Yes",P7<>"Yes"),0,1) -> 0 | AA7: =AVERAGE(W7:Z7) -> 0.625 | AB7: =IF(AA7>=0.75,"High",IF(AA7>=0.4,"Medium","Low")) -> Medium | AC7: =MAX(0,V7)*IF(AB7="High",1,IF(AB7="Medium",0.6,0.2)) -> 30.6 | AD7: =IF(OR(C7="Yes",H7<>"Yes",E7>=70,G7>=F7,Y7=0,Z7=0),"HOLD / EXPERT REVIEW",IF(V7>0,"REVIEW CANDIDATE","NO POSITIVE SAVING")) -> HOLD / EXPERT REVIEW | AE7: Critical workload; hard hold
A8: VM-07 | B8: Internal utility | C8: No | D8: 2 | E8: 12 | F8: 8 | G8: 2 | H8: Yes | I8: 30 | J8: 0.2 | K8: 1 | L8: 1 | M8: No | N8: No | O8: Yes | P8: Yes | Q8: =D8*E8/100 -> 0.24 | R8: =MAX(1,ROUNDUP(Q8/Assumptions!$B$5-0.000000001,0)) -> 1 | S8: =MAX(1,ROUNDUP(G8/Assumptions!$B$6-0.000000001,0)) -> 3 | T8: =D8*Assumptions!$B$3+F8*Assumptions!$B$4 -> 48 | U8: =R8*Assumptions!$B$3+S8*Assumptions!$B$4 -> 21 | V8: =T8-U8 -> 27 | W8: =IF(AND(H8="Yes",I8>=30),1,IF(AND(H8="Yes",I8>=14),0.5,0)) -> 1 | X8: =IF(J8<0.3,1,IF(J8<0.6,0.5,0)) -> 1 | Y8: =IF(OR(K8>10,L8>5,M8="Yes",N8="Yes"),0,IF(OR(K8>=5,L8>=3,M8="Minor",N8="Minor"),0.5,1)) -> 1 | Z8: =IF(OR(C8="Yes",O8<>"Yes",P8<>"Yes"),0,1) -> 1 | AA8: =AVERAGE(W8:Z8) -> 1 | AB8: =IF(AA8>=0.75,"High",IF(AA8>=0.4,"Medium","Low")) -> High | AC8: =MAX(0,V8)*IF(AB8="High",1,IF(AB8="Medium",0.6,0.2)) -> 27 | AD8: =IF(OR(C8="Yes",H8<>"Yes",E8>=70,G8>=F8,Y8=0,Z8=0),"HOLD / EXPERT REVIEW",IF(V8>0,"REVIEW CANDIDATE","NO POSITIVE SAVING")) -> REVIEW CANDIDATE | AE8: Hypothetical
A9: VM-08 | B9: API service | C9: No | D9: 8 | E9: 48 | F9: 32 | G9: 18 | H9: No | I9: 10 | J9: 0.4 | K9: 2 | L9: 1 | M9: No | N9: No | O9: Yes | P9: Yes | Q9: =D9*E9/100 -> 3.84 | R9: =MAX(1,ROUNDUP(Q9/Assumptions!$B$5-0.000000001,0)) -> 6 | S9: =MAX(1,ROUNDUP(G9/Assumptions!$B$6-0.000000001,0)) -> 23 | T9: =D9*Assumptions!$B$3+F9*Assumptions!$B$4 -> 192 | U9: =R9*Assumptions!$B$3+S9*Assumptions!$B$4 -> 141 | V9: =T9-U9 -> 51 | W9: =IF(AND(H9="Yes",I9>=30),1,IF(AND(H9="Yes",I9>=14),0.5,0)) -> 0 | X9: =IF(J9<0.3,1,IF(J9<0.6,0.5,0)) -> 0.5 | Y9: =IF(OR(K9>10,L9>5,M9="Yes",N9="Yes"),0,IF(OR(K9>=5,L9>=3,M9="Minor",N9="Minor"),0.5,1)) -> 1 | Z9: =IF(OR(C9="Yes",O9<>"Yes",P9<>"Yes"),0,1) -> 1 | AA9: =AVERAGE(W9:Z9) -> 0.625 | AB9: =IF(AA9>=0.75,"High",IF(AA9>=0.4,"Medium","Low")) -> Medium | AC9: =MAX(0,V9)*IF(AB9="High",1,IF(AB9="Medium",0.6,0.2)) -> 30.6 | AD9: =IF(OR(C9="Yes",H9<>"Yes",E9>=70,G9>=F9,Y9=0,Z9=0),"HOLD / EXPERT REVIEW",IF(V9>0,"REVIEW CANDIDATE","NO POSITIVE SAVING")) -> HOLD / EXPERT REVIEW | AE9: Incomplete telemetry; hard hold
A10: VM-09 | B10: Analytics worker | C10: No | D10: 16 | E10: 67 | F10: 64 | G10: 40 | H10: Yes | I10: 30 | J10: 0.4 | K10: 3 | L10: 2 | M10: No | N10: No | O10: Yes | P10: Yes | Q10: =D10*E10/100 -> 10.72 | R10: =MAX(1,ROUNDUP(Q10/Assumptions!$B$5-0.000000001,0)) -> 16 | S10: =MAX(1,ROUNDUP(G10/Assumptions!$B$6-0.000000001,0)) -> 50 | T10: =D10*Assumptions!$B$3+F10*Assumptions!$B$4 -> 384 | U10: =R10*Assumptions!$B$3+S10*Assumptions!$B$4 -> 342 | V10: =T10-U10 -> 42 | W10: =IF(AND(H10="Yes",I10>=30),1,IF(AND(H10="Yes",I10>=14),0.5,0)) -> 1 | X10: =IF(J10<0.3,1,IF(J10<0.6,0.5,0)) -> 0.5 | Y10: =IF(OR(K10>10,L10>5,M10="Yes",N10="Yes"),0,IF(OR(K10>=5,L10>=3,M10="Minor",N10="Minor"),0.5,1)) -> 1 | Z10: =IF(OR(C10="Yes",O10<>"Yes",P10<>"Yes"),0,1) -> 1 | AA10: =AVERAGE(W10:Z10) -> 0.875 | AB10: =IF(AA10>=0.75,"High",IF(AA10>=0.4,"Medium","Low")) -> High | AC10: =MAX(0,V10)*IF(AB10="High",1,IF(AB10="Medium",0.6,0.2)) -> 42 | AD10: =IF(OR(C10="Yes",H10<>"Yes",E10>=70,G10>=F10,Y10=0,Z10=0),"HOLD / EXPERT REVIEW",IF(V10>0,"REVIEW CANDIDATE","NO POSITIVE SAVING")) -> REVIEW CANDIDATE | AE10: Illustrative variability; review peak and batch windows
A11: VM-10 | B11: Legacy service | C11: Yes | D11: 4 | E11: 20 | F11: 32 | G11: 25 | H11: Yes | I11: 30 | J11: 0.4 | K11: 2 | L11: 1 | M11: No | N11: No | O11: Yes | P11: Yes | Q11: =D11*E11/100 -> 0.8 | R11: =MAX(1,ROUNDUP(Q11/Assumptions!$B$5-0.000000001,0)) -> 2 | S11: =MAX(1,ROUNDUP(G11/Assumptions!$B$6-0.000000001,0)) -> 32 | T11: =D11*Assumptions!$B$3+F11*Assumptions!$B$4 -> 144 | U11: =R11*Assumptions!$B$3+S11*Assumptions!$B$4 -> 120 | V11: =T11-U11 -> 24 | W11: =IF(AND(H11="Yes",I11>=30),1,IF(AND(H11="Yes",I11>=14),0.5,0)) -> 1 | X11: =IF(J11<0.3,1,IF(J11<0.6,0.5,0)) -> 0.5 | Y11: =IF(OR(K11>10,L11>5,M11="Yes",N11="Yes"),0,IF(OR(K11>=5,L11>=3,M11="Minor",N11="Minor"),0.5,1)) -> 1 | Z11: =IF(OR(C11="Yes",O11<>"Yes",P11<>"Yes"),0,1) -> 0 | AA11: =AVERAGE(W11:Z11) -> 0.625 | AB11: =IF(AA11>=0.75,"High",IF(AA11>=0.4,"Medium","Low")) -> Medium | AC11: =MAX(0,V11)*IF(AB11="High",1,IF(AB11="Medium",0.6,0.2)) -> 14.4 | AD11: =IF(OR(C11="Yes",H11<>"Yes",E11>=70,G11>=F11,Y11=0,Z11=0),"HOLD / EXPERT REVIEW",IF(V11>0,"REVIEW CANDIDATE","NO POSITIVE SAVING")) -> HOLD / EXPERT REVIEW | AE11: Critical workload; hard hold
A12: VM-11 | B12: Dev/test | C12: No | D12: 8 | E12: 9 | F12: 32 | G12: 4 | H12: Yes | I12: 30 | J12: 0.2 | K12: 1 | L12: 1 | M12: No | N12: No | O12: Yes | P12: Yes | Q12: =D12*E12/100 -> 0.72 | R12: =MAX(1,ROUNDUP(Q12/Assumptions!$B$5-0.000000001,0)) -> 2 | S12: =MAX(1,ROUNDUP(G12/Assumptions!$B$6-0.000000001,0)) -> 5 | T12: =D12*Assumptions!$B$3+F12*Assumptions!$B$4 -> 192 | U12: =R12*Assumptions!$B$3+S12*Assumptions!$B$4 -> 39 | V12: =T12-U12 -> 153 | W12: =IF(AND(H12="Yes",I12>=30),1,IF(AND(H12="Yes",I12>=14),0.5,0)) -> 1 | X12: =IF(J12<0.3,1,IF(J12<0.6,0.5,0)) -> 1 | Y12: =IF(OR(K12>10,L12>5,M12="Yes",N12="Yes"),0,IF(OR(K12>=5,L12>=3,M12="Minor",N12="Minor"),0.5,1)) -> 1 | Z12: =IF(OR(C12="Yes",O12<>"Yes",P12<>"Yes"),0,1) -> 1 | AA12: =AVERAGE(W12:Z12) -> 1 | AB12: =IF(AA12>=0.75,"High",IF(AA12>=0.4,"Medium","Low")) -> High | AC12: =MAX(0,V12)*IF(AB12="High",1,IF(AB12="Medium",0.6,0.2)) -> 153 | AD12: =IF(OR(C12="Yes",H12<>"Yes",E12>=70,G12>=F12,Y12=0,Z12=0),"HOLD / EXPERT REVIEW",IF(V12>0,"REVIEW CANDIDATE","NO POSITIVE SAVING")) -> REVIEW CANDIDATE | AE12: Illustrative worked example; synthetic 30-day window
A13: VM-12 | B13: Network appliance | C13: Yes | D13: 4 | E13: 42 | F13: 8 | G13: 5 | H13: Yes | I13: 30 | J13: 0.4 | K13: 2 | L13: 1 | M13: No | N13: No | O13: Yes | P13: No | Q13: =D13*E13/100 -> 1.68 | R13: =MAX(1,ROUNDUP(Q13/Assumptions!$B$5-0.000000001,0)) -> 3 | S13: =MAX(1,ROUNDUP(G13/Assumptions!$B$6-0.000000001,0)) -> 7 | T13: =D13*Assumptions!$B$3+F13*Assumptions!$B$4 -> 72 | U13: =R13*Assumptions!$B$3+S13*Assumptions!$B$4 -> 57 | V13: =T13-U13 -> 15 | W13: =IF(AND(H13="Yes",I13>=30),1,IF(AND(H13="Yes",I13>=14),0.5,0)) -> 1 | X13: =IF(J13<0.3,1,IF(J13<0.6,0.5,0)) -> 0.5 | Y13: =IF(OR(K13>10,L13>5,M13="Yes",N13="Yes"),0,IF(OR(K13>=5,L13>=3,M13="Minor",N13="Minor"),0.5,1)) -> 1 | Z13: =IF(OR(C13="Yes",O13<>"Yes",P13<>"Yes"),0,1) -> 0 | AA13: =AVERAGE(W13:Z13) -> 0.625 | AB13: =IF(AA13>=0.75,"High",IF(AA13>=0.4,"Medium","Low")) -> Medium | AC13: =MAX(0,V13)*IF(AB13="High",1,IF(AB13="Medium",0.6,0.2)) -> 9 | AD13: =IF(OR(C13="Yes",H13<>"Yes",E13>=70,G13>=F13,Y13=0,Z13=0),"HOLD / EXPERT REVIEW",IF(V13>0,"REVIEW CANDIDATE","NO POSITIVE SAVING")) -> HOLD / EXPERT REVIEW | AE13: Critical workload and vendor constraints unverified; hard hold

Sheet Research Log
A1: Paper / source | B1: Year | C1: Problem addressed | D1: Method | E1: Dataset / environment | F1: Metrics | G1: Limitations stated by authors | H1: Potential gap relevant to VMValue | I1: Link / DOI | J1: Read status
A2: Virtualization in the Private Cloud: State of the Practice | B2: 2016 | C2: Characterizes VM resource use and provisioning in enterprise private clouds | D2: Large-scale workload characterization | E2: 90K VMs / 8K physical servers; 19 days | F2: CPU/memory provisioning, resource use, migration patterns | G2: Extract from full paper before citing any detailed limitation | H2: Use as background evidence for overprovisioning and real workload behavior | I2: https://research.ibm.com/publications/virtualization-in-the-private-cloud-state-of-the-practice | J2: Metadata/abstract checked; full-text review still needed
A3: VM consolidation steps in cloud computing: A perspective review | B3: 2025 | C3: Reviews virtual-machine consolidation | D3: Perspective review across PM detection, VM selection, placement | E3: Literature from 2015–2024 | F3: Compare consolidation phases and evaluation metrics | G3: Read full text / abstract and record exact limitations | H3: Avoid duplicating generic consolidation review; identify specific evaluation inconsistency | I3: https://doi.org/10.1016/j.simpat.2024.103034 | J3: Metadata/abstract checked; full-text review still needed
A4: A systematic literature review on contemporary and future trends in virtual machine scheduling techniques in cloud and multi-access computing | B4: 2024 | C4: Surveys VM scheduling techniques | D4: Systematic literature review | E4: Published literature | F4: Cost, energy, utilization, load balancing, scheduling methods | G4: Extract from full text | H4: Map existing methods and their objectives before defining the gap | I4: https://doi.org/10.3389/fcomp.2024.1288552 | J4: Metadata/abstract checked; full-text review still needed
A5: Rightsizing virtual machines on ESXi 8.0: vCPU, memory, and CPU topology guidance | B5: 2026 | C5: Operational guidance for VM sizing | D5: Vendor guidance / counters and review procedure | E5: VMware ESXi 8.0 | F5: CPU utilization, CPU Ready, Co-Stop, active/consumed memory, balloon/swap | G5: Vendor guidance; not an independent comparative study | H5: Translate operational counters into transparent, evidence-based review rules | I5: https://knowledge.broadcom.com/external/article/438023/rightsizing-virtual-machines-on-esxi-80.html | J5: Metadata/abstract checked; full-text review still needed
A6: Confidence interval-based overload avoidance algorithm for virtual machine placement | B6: 2022 | C6: Avoids overload during VM placement | D6: Confidence-interval-based algorithm | E6: Read full paper for environment | F6: Overload and placement outcomes | G6: Extract from full paper | H6: Compare uncertainty-aware placement concepts to risk-aware rightsizing | I6: https://doi.org/10.1002/spe.3127 | J6: Metadata/abstract checked; full-text review still needed
